pytest_test_categories/__init__.py
pytest_test_categories/errors.py
pytest_test_categories/exceptions.py
pytest_test_categories/formatting.py
pytest_test_categories/json_report.py
pytest_test_categories/plugin.py
pytest_test_categories/reporting.py
pytest_test_categories/test_bases.py
pytest_test_categories/timers.py
pytest_test_categories/timing.py
pytest_test_categories/types.py
pytest_test_categories/violation_tracking.py
pytest_test_categories/xdist_compat.py
pytest_test_categories/adapters/__init__.py
pytest_test_categories/adapters/database.py
pytest_test_categories/adapters/external_systems.py
pytest_test_categories/adapters/fake_database.py
pytest_test_categories/adapters/fake_external_systems.py
pytest_test_categories/adapters/fake_filesystem.py
pytest_test_categories/adapters/fake_network.py
pytest_test_categories/adapters/fake_process.py
pytest_test_categories/adapters/fake_sleep.py
pytest_test_categories/adapters/fake_threading.py
pytest_test_categories/adapters/filesystem.py
pytest_test_categories/adapters/network.py
pytest_test_categories/adapters/process.py
pytest_test_categories/adapters/pytest_adapter.py
pytest_test_categories/adapters/sleep.py
pytest_test_categories/adapters/threading.py
pytest_test_categories/distribution/__init__.py
pytest_test_categories/distribution/config.py
pytest_test_categories/distribution/stats.py
pytest_test_categories/ports/__init__.py
pytest_test_categories/ports/database.py
pytest_test_categories/ports/external_systems.py
pytest_test_categories/ports/filesystem.py
pytest_test_categories/ports/network.py
pytest_test_categories/ports/process.py
pytest_test_categories/ports/sleep.py
pytest_test_categories/ports/threading.py
pytest_test_categories/services/__init__.py
pytest_test_categories/services/distribution_validation.py
pytest_test_categories/services/hermeticity_summary.py
pytest_test_categories/services/test_counting.py
pytest_test_categories/services/test_discovery.py
pytest_test_categories-1.1.0.dist-info/METADATA
pytest_test_categories-1.1.0.dist-info/WHEEL
pytest_test_categories-1.1.0.dist-info/entry_points.txt
pytest_test_categories-1.1.0.dist-info/licenses/LICENSE
pytest_test_categories-1.1.0.dist-info/RECORD
