Metadata-Version: 2.4
Name: pytest-test-categories
Version: 1.1.0
Summary: A pytest plugin to enforce test timing constraints and size distributions.
Project-URL: Homepage, https://github.com/mikelane/pytest-test-categories
Project-URL: Documentation, https://pytest-test-categories.readthedocs.io
Project-URL: Repository, https://github.com/mikelane/pytest-test-categories
Project-URL: Changelog, https://github.com/mikelane/pytest-test-categories/blob/main/CHANGELOG.md
Project-URL: Bug Tracker, https://github.com/mikelane/pytest-test-categories/issues
Author-email: Mike Lane <mikelane@gmail.com>
License: MIT
License-File: LICENSE
Keywords: ci-cd,flaky-tests,hermetic,integration-testing,pytest,test-categories,test-pyramid,test-timing,testing,unit-testing
Classifier: Development Status :: 5 - Production/Stable
Classifier: Environment :: Console
Classifier: Environment :: Plugins
Classifier: Framework :: Pytest
Classifier: Intended Audience :: Developers
Classifier: License :: OSI Approved :: MIT License
Classifier: Operating System :: OS Independent
Classifier: Programming Language :: Python :: 3
Classifier: Programming Language :: Python :: 3.11
Classifier: Programming Language :: Python :: 3.12
Classifier: Programming Language :: Python :: 3.13
Classifier: Programming Language :: Python :: 3.14
Classifier: Topic :: Software Development :: Quality Assurance
Classifier: Topic :: Software Development :: Testing
Classifier: Topic :: Software Development :: Testing :: Unit
Classifier: Typing :: Typed
Requires-Python: >=3.11
Requires-Dist: beartype>=0.22.5
Requires-Dist: icontract>=2.7.1
Requires-Dist: pydantic>=2.12.4
Requires-Dist: pytest>=8.4.2
